pytorch_treadmill-0.6.5.dist-info/licenses/LICENSE
tests/__init__.py
tests/test_config.py
tests/test_metrics.py
tests/test_trainer.py
treadmill/__init__.py
treadmill/callbacks.py
treadmill/config.py
treadmill/metrics.py
treadmill/report.py
treadmill/trainer.py
treadmill/utils.py
pytorch_treadmill-0.6.5.dist-info/METADATA
pytorch_treadmill-0.6.5.dist-info/WHEEL
pytorch_treadmill-0.6.5.dist-info/top_level.txt
pytorch_treadmill-0.6.5.dist-info/RECORD
