Metadata-Version: 2.4
Name: pytorch-treadmill
Version: 0.6.5
Summary: A Clean and Modular PyTorch Training Framework
Home-page: https://github.com/MayukhSobo/treadmill
Author: Mayukh Sarkar
Author-email: Mayukh Sarkar <mayukh2012@hotmail.com>
Maintainer-email: Mayukh Sarkar <mayukh2012@hotmail.com>
License: MIT
Project-URL: homepage, https://github.com/MayukhSobo/treadmill
Project-URL: documentation, https://mayukhsobo.github.io/treadmill/
Project-URL: repository, https://github.com/MayukhSobo/treadmill
Project-URL: changelog, https://github.com/MayukhSobo/treadmill/blob/main/CHANGELOG.md
Keywords: pytorch,deep learning,training,machine learning,neural networks
Classifier: Development Status :: 3 - Alpha
Classifier: Intended Audience :: Developers
Classifier: Intended Audience :: Science/Research
Classifier: License :: OSI Approved :: MIT License
Classifier: Operating System :: OS Independent
Classifier: Programming Language :: Python :: 3
Classifier: Programming Language :: Python :: 3.8
Classifier: Programming Language :: Python :: 3.9
Classifier: Programming Language :: Python :: 3.10
Classifier: Programming Language :: Python :: 3.11
Classifier: Topic :: Scientific/Engineering :: Artificial Intelligence
Classifier: Topic :: Software Development :: Libraries :: Python Modules
Requires-Python: >=3.8
License-File: LICENSE
Requires-Dist: torch>=1.12.0
Requires-Dist: torchvision>=0.13.0
Requires-Dist: numpy>=1.21.0
Requires-Dist: rich>=12.0.0
Requires-Dist: torchinfo>=1.7.0
Requires-Dist: scikit-learn>=1.0.0
Requires-Dist: click>=8.0.0
Requires-Dist: pytz>=2021.3
Requires-Dist: psutil>=5.8.0
Requires-Dist: pynvml>=8.0.4
Provides-Extra: dev
Requires-Dist: pytest>=7.0.0; extra == "dev"
Requires-Dist: pytest-cov>=4.0.0; extra == "dev"
Requires-Dist: black>=22.0.0; extra == "dev"
Requires-Dist: flake8>=4.0.0; extra == "dev"
Requires-Dist: mypy>=0.950; extra == "dev"
Requires-Dist: build>=0.8.0; extra == "dev"
Requires-Dist: twine>=4.0.0; extra == "dev"
Provides-Extra: examples
Requires-Dist: torchvision>=0.13.0; extra == "examples"
Requires-Dist: scikit-learn>=1.0.0; extra == "examples"
Provides-Extra: full
Requires-Dist: torchinfo>=1.7.0; extra == "full"
Requires-Dist: matplotlib>=3.5.0; extra == "full"
Requires-Dist: seaborn>=0.11.0; extra == "full"
Requires-Dist: tensorboard>=2.8.0; extra == "full"
Requires-Dist: onnx>=1.12.0; extra == "full"
Requires-Dist: safetensors>=0.3.0; extra == "full"
Requires-Dist: sphinx>=5.0.0; extra == "full"
Requires-Dist: sphinx-rtd-theme>=1.0.0; extra == "full"
Requires-Dist: myst-parser>=0.18.0; extra == "full"
Dynamic: author
Dynamic: home-page
Dynamic: license-file
Dynamic: requires-python
